bigstream/__init__.py
bigstream/align.py
bigstream/application_pipelines.py
bigstream/configure_irm.py
bigstream/distributed_align.py
bigstream/distributed_io_utility.py
bigstream/distributed_transform.py
bigstream/features.py
bigstream/io_utility.py
bigstream/level_set.py
bigstream/metrics.py
bigstream/motion_correct.py
bigstream/piecewise_align.py
bigstream/piecewise_transform.py
bigstream/stitch.py
bigstream/transform.py
bigstream/utility.py
bigstream-4.0.0.dist-info/LICENSE.md
bigstream-4.0.0.dist-info/METADATA
bigstream-4.0.0.dist-info/WHEEL
bigstream-4.0.0.dist-info/top_level.txt
bigstream-4.0.0.dist-info/RECORD
